.hgignore
.hgtags
.travis.yml
LICENSE
MANIFEST.in
README.md
dev-requirements.txt
gulpfile.js
package-lock.json
package.json
pytest.ini
requirements.txt
setup.cfg
setup.py
tasks.py
tox.ini
wk.py
Wikked.egg-info/PKG-INFO
Wikked.egg-info/SOURCES.txt
Wikked.egg-info/dependency_links.txt
Wikked.egg-info/entry_points.txt
Wikked.egg-info/not-zip-safe
Wikked.egg-info/requires.txt
Wikked.egg-info/top_level.txt
benchmarks/Benchmark.conf.sample
benchmarks/test_benchmark.py
monkeys/release.py
tests/__init__.py
tests/mock.py
tests/test_auth.py
tests/test_db.py
tests/test_formatter.py
tests/test_mock.py
tests/test_page.py
tests/test_resolver.py
tools/import_mediawiki.py
wikked/__init__.py
wikked/__version__.py
wikked/auth.py
wikked/bcryptfallback.py
wikked/cache.py
wikked/commonroutes.py
wikked/endpoint.py
wikked/formatter.py
wikked/fs.py
wikked/page.py
wikked/resolver.py
wikked/scheduler.py
wikked/settings.py
wikked/tasks.py
wikked/utils.py
wikked/web.py
wikked/wiki.py
wikked/witch.py
wikked/wsgiutil.py
wikked/api/__init__.py
wikked/api/admin.py
wikked/api/edit.py
wikked/api/history.py
wikked/api/read.py
wikked/api/special.py
wikked/api/user.py
wikked/assets/.rbuild.js
wikked/assets/css/jouvence.less
wikked/assets/css/syntax.css
wikked/assets/css/wikked.less
wikked/assets/css/wmd.css
wikked/assets/css/wikked/alerts.less
wikked/assets/css/wikked/base.less
wikked/assets/css/wikked/main.less
wikked/assets/css/wikked/nav.less
wikked/assets/css/wikked/page.less
wikked/assets/img/creampaper.png
wikked/assets/img/creampaper_@2X.png
wikked/assets/img/gray_jean.png
wikked/assets/img/gray_jean_@2X.jpg
wikked/assets/img/grid.png
wikked/assets/img/grid_@2X.png
wikked/assets/img/markdown-32x20-solid.png
wikked/assets/img/markdown-32x20.png
wikked/assets/img/retina_dust.png
wikked/assets/img/retina_dust_@2X.png
wikked/assets/img/wmd-buttons.png
wikked/assets/js/wikked.app.js
wikked/assets/js/wikked.edit.js
wikked/assets/js/wikked/app.js
wikked/assets/js/wikked/edit.js
wikked/commands/__init__.py
wikked/commands/base.py
wikked/commands/manage.py
wikked/commands/query.py
wikked/commands/users.py
wikked/commands/web.py
wikked/db/__init__.py
wikked/db/base.py
wikked/db/sql.py
wikked/indexer/__init__.py
