Metadata-Version: 1.1
Name: Wikked
Version: 0.8.0
Summary: A wiki engine entirely managed with text files stored in a revision control system.
Home-page: https://github.com/ludovicchabant/Wikked
Author: Ludovic Chabant
Author-email: ludovic@chabant.com
License: Apache 2.0
Keywords: wiki mercurial hg git
Platform: UNKNOWN
Classifier: Development Status :: 3 - Alpha
Classifier: License :: OSI Approved :: Apache Software License
Classifier: Environment :: Console
Classifier: Operating System :: MacOS :: MacOS X
Classifier: Operating System :: Unix
Classifier: Operating System :: POSIX
Classifier: Operating System :: Microsoft :: Windows
Classifier: Programming Language :: Python
